pypsm/__init__.py
pypsm/psargument.py
pypsm/psfunction.py
pypsm/psmodule.py
pypsm/pstypes.py
pypsm-0.1.4.dist-info/METADATA
pypsm-0.1.4.dist-info/RECORD
pypsm-0.1.4.dist-info/WHEEL
pypsm-0.1.4.dist-info/top_level.txt
