Metadata-Version: 2.1
Name: pypsm
Version: 0.1.4
Summary: Write PowerShell modules with python
Home-page: UNKNOWN
Author: Philip Stoop
Author-email: stoopphilip97@gmail.com
License: UNKNOWN
Platform: UNKNOWN
